setup.cfg
setup.py
where/__init__.py
where.egg-info/PKG-INFO
where.egg-info/SOURCES.txt
where.egg-info/dependency_links.txt
where.egg-info/requires.txt
where.egg-info/top_level.txt