Metadata-Version: 1.0
Name: where
Version: 1.0.1
Summary: Locates absolute file paths like the Windows 'where' or the Linux 'which' utility.
Home-page: https://github.com/hweickert/where
Author: Henry Weickert
Author-email: henryweickert@gmail.com
License: UNKNOWN
Keywords: where,which
Platform: UNKNOWN
